LICENSE
MANIFEST.in
README.rst
requirements.txt
setup.py
mongo_memoize/__init__.py
mongo_memoize/decorator.py
mongo_memoize/key_generator.py
mongo_memoize/serializer.py
mongo_memoize.egg-info/PKG-INFO
mongo_memoize.egg-info/SOURCES.txt
mongo_memoize.egg-info/dependency_links.txt
mongo_memoize.egg-info/requires.txt
mongo_memoize.egg-info/top_level.txt
tests/__init__.py
tests/test_decorator.py
tests/test_key_generator.py
tests/test_serializer.py