Metadata-Version: 1.1
Name: mongo-memoize
Version: 0.0.3
Summary: A Python decorator library for caching function results in MongoDB
Home-page: http://github.com/ikuyamada/mongo-memoize/
Author: Ikuya Yamada
Author-email: ikuya@ikuya.net
License: Copyright 2014 Ikuya Yamada
